LICENSE.txt
README.md
__init__.py
find_datacol_diff.py
utils.py
pyspark_datacol_diff.egg-info/PKG-INFO
pyspark_datacol_diff.egg-info/SOURCES.txt
pyspark_datacol_diff.egg-info/dependency_links.txt
pyspark_datacol_diff.egg-info/requires.txt
pyspark_datacol_diff.egg-info/top_level.txt
pysparkdatacoldiff/__init__.py
pysparkdatacoldiff/find_dataframe_diff.py
pyspark_datacol_diff-0.0.6.dist-info/LICENSE.txt
pyspark_datacol_diff-0.0.6.dist-info/METADATA
pyspark_datacol_diff-0.0.6.dist-info/WHEEL
pyspark_datacol_diff-0.0.6.dist-info/top_level.txt
pyspark_datacol_diff-0.0.6.dist-info/RECORD
